{
  "swagger": "2.0",
  "info": {
    "title": "Users Rest API",
    "version": "1.0.0",
    "description": ""
  },
  "host": "localhost:5000",
  "basePath": "/",
  "schemes": [
    "http"
  ],
  "paths": {
    "/registration": {
      "post": {
        "tags": [
          "Auths"
        ],
        "description": "Register a new user.",
        "parameters": [
          {
            "name": "body",
            "in": "body",
            "schema": {
              "type": "object",
              "properties": {
                "email": {
                  "example": "any"
                },
                "password": {
                  "example": "any"
                }
              }
            }
          }
        ],
        "responses": {
          "default": {
            "description": ""
          }
        }
      }
    },
    "/activation/{activationToken}": {
      "get": {
        "tags": [
          "Auths"
        ],
        "description": "Activate new user.",
        "parameters": [
          {
            "name": "activationToken",
            "in": "path",
            "required": true,
            "type": "string"
          }
        ],
        "responses": {
          "default": {
            "description": ""
          }
        }
      }
    },
    "/login": {
      "post": {
        "tags": [
          "Auths"
        ],
        "description": "Login user.",
        "parameters": [
          {
            "name": "body",
            "in": "body",
            "schema": {
              "type": "object",
              "properties": {
                "email": {
                  "example": "any"
                },
                "password": {
                  "example": "any"
                }
              }
            }
          }
        ],
        "responses": {
          "default": {
            "description": ""
          }
        }
      }
    },
    "/reset-password": {
      "post": {
        "tags": [
          "Auths"
        ],
        "description": "Reset password of chosen user.",
        "parameters": [
          {
            "name": "body",
            "in": "body",
            "schema": {
              "type": "object",
              "properties": {
                "email": {
                  "example": "any"
                }
              }
            }
          }
        ],
        "responses": {
          "default": {
            "description": ""
          }
        }
      }
    },
    "/reset-password/{resetPasswordToken}": {
      "get": {
        "tags": [
          "Auths"
        ],
        "description": "Check the reset password token.",
        "parameters": [
          {
            "name": "resetPasswordToken",
            "in": "path",
            "required": true,
            "type": "string"
          }
        ],
        "responses": {
          "default": {
            "description": ""
          }
        }
      },
      "post": {
        "tags": [
          "Auths"
        ],
        "description": "Reset password of chosen user.",
        "parameters": [
          {
            "name": "resetPasswordToken",
            "in": "path",
            "required": true,
            "type": "string"
          },
          {
            "name": "body",
            "in": "body",
            "schema": {
              "type": "object",
              "properties": {
                "password": {
                  "example": "any"
                }
              }
            }
          }
        ],
        "responses": {
          "default": {
            "description": ""
          }
        }
      }
    },
    "/refresh": {
      "get": {
        "tags": [
          "Auths"
        ],
        "description": "Refresh token.",
        "responses": {
          "default": {
            "description": ""
          }
        }
      }
    },
    "/logout": {
      "post": {
        "tags": [
          "Auths"
        ],
        "description": "Logout user.",
        "responses": {
          "default": {
            "description": ""
          }
        }
      }
    },
    "/users": {
      "get": {
        "tags": [
          "Users"
        ],
        "description": "Return all activated users.",
        "parameters": [
          {
            "name": "authorization",
            "in": "header",
            "type": "string"
          }
        ],
        "responses": {
          "401": {
            "description": "Unauthorized"
          }
        }
      }
    }
  }
}